{
    "generated_at":  "2026-07-12T17:59:08.430568Z",
    "run_id":  "live_20260712_124534",
    "sport":  "MLB",
    "model_engaged_at":  "2026-07-12T12:50:55.117200-05:00",
    "model_engaged_at_local":  "2026-07-12 12:50 PM CT",
    "model_engaged_label":  "model engaged at 2026-07-12 12:50 PM CT",
    "picks":  [
                  {
                      "player":  "Mitch Bratt",
                      "team":  "AZ",
                      "opp":  "LAD",
                      "stat":  "WALKS ALLOWED",
                      "line":  0.5,
                      "dir":  "OVER",
                      "tier":  "GOBLIN",
                      "p_cal":  0.871107
                  },
                  {
                      "player":  "Germán Márquez",
                      "team":  "SD",
                      "opp":  "TOR",
                      "stat":  "EARNED RUNS ALLOWED",
                      "line":  2.5,
                      "dir":  "UNDER",
                      "tier":  "STANDARD",
                      "p_cal":  0.758308
                  },
                  {
                      "player":  "Jeremy Peña",
                      "team":  "HOU",
                      "opp":  "TEX",
                      "stat":  "RBIS",
                      "line":  0.5,
                      "dir":  "OVER",
                      "tier":  "DEMON",
                      "p_cal":  0.664135
                  },
                  {
                      "player":  "Trevor McDonald",
                      "team":  "SF",
                      "opp":  "COL",
                      "stat":  "WALKS ALLOWED",
                      "line":  0.5,
                      "dir":  "OVER",
                      "tier":  "GOBLIN",
                      "p_cal":  0.870405
                  },
                  {
                      "player":  "Jacob Wilson",
                      "team":  "ATH",
                      "opp":  "CWS",
                      "stat":  "HITS",
                      "line":  0.5,
                      "dir":  "OVER",
                      "tier":  "GOBLIN",
                      "p_cal":  0.865002
                  },
                  {
                      "player":  "MacKenzie Gore",
                      "team":  "TEX",
                      "opp":  "HOU",
                      "stat":  "WALKS ALLOWED",
                      "line":  0.5,
                      "dir":  "OVER",
                      "tier":  "GOBLIN",
                      "p_cal":  0.85293
                  },
                  {
                      "player":  "Taj Bradley",
                      "team":  "MIN",
                      "opp":  "LAA",
                      "stat":  "WALKS ALLOWED",
                      "line":  0.5,
                      "dir":  "OVER",
                      "tier":  "GOBLIN",
                      "p_cal":  0.843871
                  },
                  {
                      "player":  "Cristian Javier",
                      "team":  "HOU",
                      "opp":  "TEX",
                      "stat":  "WALKS ALLOWED",
                      "line":  0.5,
                      "dir":  "OVER",
                      "tier":  "GOBLIN",
                      "p_cal":  0.843813
                  },
                  {
                      "player":  "Michael Lorenzen",
                      "team":  "COL",
                      "opp":  "SF",
                      "stat":  "WALKS ALLOWED",
                      "line":  0.5,
                      "dir":  "OVER",
                      "tier":  "GOBLIN",
                      "p_cal":  0.841159
                  },
                  {
                      "player":  "Noah Schultz",
                      "team":  "CWS",
                      "opp":  "ATH",
                      "stat":  "WALKS ALLOWED",
                      "line":  0.5,
                      "dir":  "OVER",
                      "tier":  "GOBLIN",
                      "p_cal":  0.833026
                  },
                  {
                      "player":  "JR Ritchie",
                      "team":  "ATL",
                      "opp":  "STL",
                      "stat":  "HITS ALLOWED",
                      "line":  2.5,
                      "dir":  "OVER",
                      "tier":  "GOBLIN",
                      "p_cal":  0.829525
                  },
                  {
                      "player":  "Yordan Alvarez",
                      "team":  "HOU",
                      "opp":  "TEX",
                      "stat":  "HITS",
                      "line":  0.5,
                      "dir":  "OVER",
                      "tier":  "GOBLIN",
                      "p_cal":  0.814105
                  },
                  {
                      "player":  "Jung Hoo Lee",
                      "team":  "SF",
                      "opp":  "COL",
                      "stat":  "HITS",
                      "line":  0.5,
                      "dir":  "OVER",
                      "tier":  "GOBLIN",
                      "p_cal":  0.805181
                  },
                  {
                      "player":  "Casey Schmitt",
                      "team":  "SF",
                      "opp":  "COL",
                      "stat":  "HITS",
                      "line":  0.5,
                      "dir":  "OVER",
                      "tier":  "GOBLIN",
                      "p_cal":  0.802372
                  },
                  {
                      "player":  "Drew Gilbert",
                      "team":  "SF",
                      "opp":  "COL",
                      "stat":  "HITS",
                      "line":  0.5,
                      "dir":  "OVER",
                      "tier":  "GOBLIN",
                      "p_cal":  0.799869
                  },
                  {
                      "player":  "Mike Trout",
                      "team":  "LAA",
                      "opp":  "MIN",
                      "stat":  "HITS+RUNS+RBIS",
                      "line":  0.5,
                      "dir":  "OVER",
                      "tier":  "GOBLIN",
                      "p_cal":  0.796179
                  },
                  {
                      "player":  "Kyle Karros",
                      "team":  "COL",
                      "opp":  "SF",
                      "stat":  "HITS",
                      "line":  0.5,
                      "dir":  "OVER",
                      "tier":  "GOBLIN",
                      "p_cal":  0.795761
                  },
                  {
                      "player":  "Luis Arraez",
                      "team":  "SF",
                      "opp":  "COL",
                      "stat":  "HITS",
                      "line":  0.5,
                      "dir":  "OVER",
                      "tier":  "GOBLIN",
                      "p_cal":  0.792672
                  },
                  {
                      "player":  "Ezequiel Duran",
                      "team":  "TEX",
                      "opp":  "HOU",
                      "stat":  "HITS",
                      "line":  0.5,
                      "dir":  "OVER",
                      "tier":  "GOBLIN",
                      "p_cal":  0.789581
                  },
                  {
                      "player":  "Ketel Marte",
                      "team":  "AZ",
                      "opp":  "LAD",
                      "stat":  "HITS+RUNS+RBIS",
                      "line":  0.5,
                      "dir":  "OVER",
                      "tier":  "GOBLIN",
                      "p_cal":  0.785565
                  },
                  {
                      "player":  "Corbin Carroll",
                      "team":  "AZ",
                      "opp":  "LAD",
                      "stat":  "HITS+RUNS+RBIS",
                      "line":  0.5,
                      "dir":  "OVER",
                      "tier":  "GOBLIN",
                      "p_cal":  0.785372
                  },
                  {
                      "player":  "Denzer Guzman",
                      "team":  "LAA",
                      "opp":  "MIN",
                      "stat":  "HITS",
                      "line":  0.5,
                      "dir":  "OVER",
                      "tier":  "GOBLIN",
                      "p_cal":  0.783464
                  },
                  {
                      "player":  "Dustin May",
                      "team":  "STL",
                      "opp":  "ATL",
                      "stat":  "WALKS ALLOWED",
                      "line":  0.5,
                      "dir":  "OVER",
                      "tier":  "GOBLIN",
                      "p_cal":  0.781601
                  },
                  {
                      "player":  "Emmet Sheehan",
                      "team":  "LAD",
                      "opp":  "AZ",
                      "stat":  "EARNED RUNS ALLOWED",
                      "line":  0.5,
                      "dir":  "OVER",
                      "tier":  "GOBLIN",
                      "p_cal":  0.779601
                  },
                  {
                      "player":  "Mookie Betts",
                      "team":  "LAD",
                      "opp":  "AZ",
                      "stat":  "HITS+RUNS+RBIS",
                      "line":  0.5,
                      "dir":  "OVER",
                      "tier":  "GOBLIN",
                      "p_cal":  0.775336
                  },
                  {
                      "player":  "Munetaka Murakami",
                      "team":  "CWS",
                      "opp":  "ATH",
                      "stat":  "HITS+RUNS+RBIS",
                      "line":  0.5,
                      "dir":  "OVER",
                      "tier":  "GOBLIN",
                      "p_cal":  0.771098
                  },
                  {
                      "player":  "Royce Lewis",
                      "team":  "MIN",
                      "opp":  "LAA",
                      "stat":  "HITS+RUNS+RBIS",
                      "line":  0.5,
                      "dir":  "OVER",
                      "tier":  "GOBLIN",
                      "p_cal":  0.766364
                  },
                  {
                      "player":  "Rafael Devers",
                      "team":  "SF",
                      "opp":  "COL",
                      "stat":  "HITS",
                      "line":  0.5,
                      "dir":  "OVER",
                      "tier":  "GOBLIN",
                      "p_cal":  0.764744
                  },
                  {
                      "player":  "Freddie Freeman",
                      "team":  "LAD",
                      "opp":  "AZ",
                      "stat":  "HITS+RUNS+RBIS",
                      "line":  0.5,
                      "dir":  "OVER",
                      "tier":  "GOBLIN",
                      "p_cal":  0.761739
                  },
                  {
                      "player":  "TJ Rumfield",
                      "team":  "COL",
                      "opp":  "SF",
                      "stat":  "HITS",
                      "line":  0.5,
                      "dir":  "OVER",
                      "tier":  "GOBLIN",
                      "p_cal":  0.76125
                  },
                  {
                      "player":  "Jo Adell",
                      "team":  "LAA",
                      "opp":  "MIN",
                      "stat":  "HITS+RUNS+RBIS",
                      "line":  0.5,
                      "dir":  "OVER",
                      "tier":  "GOBLIN",
                      "p_cal":  0.754553
                  },
                  {
                      "player":  "Ivan Herrera",
                      "team":  "STL",
                      "opp":  "ATL",
                      "stat":  "HITS+RUNS+RBIS",
                      "line":  0.5,
                      "dir":  "OVER",
                      "tier":  "GOBLIN",
                      "p_cal":  0.754402
                  },
                  {
                      "player":  "Jake McCarthy",
                      "team":  "COL",
                      "opp":  "SF",
                      "stat":  "HITS",
                      "line":  0.5,
                      "dir":  "OVER",
                      "tier":  "GOBLIN",
                      "p_cal":  0.753648
                  },
                  {
                      "player":  "Ryan Jeffers",
                      "team":  "MIN",
                      "opp":  "LAA",
                      "stat":  "HITS+RUNS+RBIS",
                      "line":  0.5,
                      "dir":  "OVER",
                      "tier":  "GOBLIN",
                      "p_cal":  0.753285
                  },
                  {
                      "player":  "Jose Altuve",
                      "team":  "HOU",
                      "opp":  "TEX",
                      "stat":  "HITS+RUNS+RBIS",
                      "line":  0.5,
                      "dir":  "OVER",
                      "tier":  "GOBLIN",
                      "p_cal":  0.751737
                  },
                  {
                      "player":  "Miguel Vargas",
                      "team":  "CWS",
                      "opp":  "ATH",
                      "stat":  "HITS+RUNS+RBIS",
                      "line":  0.5,
                      "dir":  "OVER",
                      "tier":  "GOBLIN",
                      "p_cal":  0.748278
                  },
                  {
                      "player":  "Cam Smith",
                      "team":  "HOU",
                      "opp":  "TEX",
                      "stat":  "HITS+RUNS+RBIS",
                      "line":  0.5,
                      "dir":  "OVER",
                      "tier":  "GOBLIN",
                      "p_cal":  0.748012
                  },
                  {
                      "player":  "Andy Pages",
                      "team":  "LAD",
                      "opp":  "AZ",
                      "stat":  "HITS+RUNS+RBIS",
                      "line":  0.5,
                      "dir":  "OVER",
                      "tier":  "GOBLIN",
                      "p_cal":  0.74769
                  },
                  {
                      "player":  "Kyle Tucker",
                      "team":  "LAD",
                      "opp":  "AZ",
                      "stat":  "HITS+RUNS+RBIS",
                      "line":  0.5,
                      "dir":  "OVER",
                      "tier":  "GOBLIN",
                      "p_cal":  0.7465
                  },
                  {
                      "player":  "Alan Roden",
                      "team":  "MIN",
                      "opp":  "LAA",
                      "stat":  "HITS",
                      "line":  0.5,
                      "dir":  "OVER",
                      "tier":  "GOBLIN",
                      "p_cal":  0.74528
                  },
                  {
                      "player":  "Shea Langeliers",
                      "team":  "ATH",
                      "opp":  "CWS",
                      "stat":  "HITS+RUNS+RBIS",
                      "line":  0.5,
                      "dir":  "OVER",
                      "tier":  "GOBLIN",
                      "p_cal":  0.745132
                  },
                  {
                      "player":  "J.T. Ginn",
                      "team":  "ATH",
                      "opp":  "CWS",
                      "stat":  "EARNED RUNS ALLOWED",
                      "line":  2.5,
                      "dir":  "UNDER",
                      "tier":  "STANDARD",
                      "p_cal":  0.744653
                  },
                  {
                      "player":  "Geraldo Perdomo",
                      "team":  "AZ",
                      "opp":  "LAD",
                      "stat":  "HITS+RUNS+RBIS",
                      "line":  0.5,
                      "dir":  "OVER",
                      "tier":  "GOBLIN",
                      "p_cal":  0.742927
                  },
                  {
                      "player":  "Lars Nootbaar",
                      "team":  "STL",
                      "opp":  "ATL",
                      "stat":  "HITS+RUNS+RBIS",
                      "line":  0.5,
                      "dir":  "OVER",
                      "tier":  "GOBLIN",
                      "p_cal":  0.742832
                  },
                  {
                      "player":  "Chase Meidroth",
                      "team":  "CWS",
                      "opp":  "ATH",
                      "stat":  "HITS+RUNS+RBIS",
                      "line":  0.5,
                      "dir":  "OVER",
                      "tier":  "GOBLIN",
                      "p_cal":  0.741667
                  },
                  {
                      "player":  "Brandon Nimmo",
                      "team":  "TEX",
                      "opp":  "HOU",
                      "stat":  "HITS+RUNS+RBIS",
                      "line":  0.5,
                      "dir":  "OVER",
                      "tier":  "GOBLIN",
                      "p_cal":  0.741315
                  },
                  {
                      "player":  "Shohei Ohtani",
                      "team":  "LAD",
                      "opp":  "AZ",
                      "stat":  "HITS+RUNS+RBIS",
                      "line":  0.5,
                      "dir":  "OVER",
                      "tier":  "GOBLIN",
                      "p_cal":  0.738816
                  },
                  {
                      "player":  "Matt Olson",
                      "team":  "ATL",
                      "opp":  "STL",
                      "stat":  "HITS+RUNS+RBIS",
                      "line":  0.5,
                      "dir":  "OVER",
                      "tier":  "GOBLIN",
                      "p_cal":  0.736548
                  },
                  {
                      "player":  "Wyatt Langford",
                      "team":  "TEX",
                      "opp":  "HOU",
                      "stat":  "HITS+RUNS+RBIS",
                      "line":  0.5,
                      "dir":  "OVER",
                      "tier":  "GOBLIN",
                      "p_cal":  0.736498
                  },
                  {
                      "player":  "Kevin Gausman",
                      "team":  "TOR",
                      "opp":  "SD",
                      "stat":  "EARNED RUNS ALLOWED",
                      "line":  2.5,
                      "dir":  "UNDER",
                      "tier":  "STANDARD",
                      "p_cal":  0.734212
                  }
              ],
    "total_legs":  3207,
    "total_slips":  0
}