{
    "generated_at":  "2026-05-29T14:59:55.486718Z",
    "run_id":  "live_20260529_095251",
    "sport":  "MLB",
    "model_engaged_at":  "2026-05-29T09:56:08.696490-05:00",
    "model_engaged_at_local":  "2026-05-29 9:56 AM CT",
    "model_engaged_label":  "model engaged at 2026-05-29 9:56 AM CT",
    "picks":  [
                  {
                      "player":  "Elly De La Cruz",
                      "team":  "CIN",
                      "opp":  "ATL",
                      "stat":  "HITTER FANTASY SCORE",
                      "line":  2.5,
                      "dir":  "OVER",
                      "tier":  "GOBLIN",
                      "p_cal":  0.84375
                  },
                  {
                      "player":  "Andrés Giménez",
                      "team":  "TOR",
                      "opp":  "BAL",
                      "stat":  "SINGLES",
                      "line":  0.5,
                      "dir":  "UNDER",
                      "tier":  "STANDARD",
                      "p_cal":  0.755371
                  },
                  {
                      "player":  "Tyler Samaniego",
                      "team":  "BOS",
                      "opp":  "CLE",
                      "stat":  "EARNED RUNS ALLOWED",
                      "line":  0.5,
                      "dir":  "OVER",
                      "tier":  "DEMON",
                      "p_cal":  0.543945
                  },
                  {
                      "player":  "Willson Contreras",
                      "team":  "BOS",
                      "opp":  "CLE",
                      "stat":  "HITTER FANTASY SCORE",
                      "line":  2.5,
                      "dir":  "OVER",
                      "tier":  "GOBLIN",
                      "p_cal":  0.841797
                  },
                  {
                      "player":  "Mark Vientos",
                      "team":  "NYM",
                      "opp":  "MIA",
                      "stat":  "HITTER FANTASY SCORE",
                      "line":  1.5,
                      "dir":  "OVER",
                      "tier":  "GOBLIN",
                      "p_cal":  0.841309
                  },
                  {
                      "player":  "Jordan Walker",
                      "team":  "STL",
                      "opp":  "CHC",
                      "stat":  "HITTER FANTASY SCORE",
                      "line":  2.5,
                      "dir":  "OVER",
                      "tier":  "GOBLIN",
                      "p_cal":  0.833008
                  },
                  {
                      "player":  "Ivan Herrera",
                      "team":  "STL",
                      "opp":  "CHC",
                      "stat":  "HITTER FANTASY SCORE",
                      "line":  2.5,
                      "dir":  "OVER",
                      "tier":  "GOBLIN",
                      "p_cal":  0.82373
                  },
                  {
                      "player":  "Spencer Steer",
                      "team":  "CIN",
                      "opp":  "ATL",
                      "stat":  "HITTER FANTASY SCORE",
                      "line":  1.5,
                      "dir":  "OVER",
                      "tier":  "GOBLIN",
                      "p_cal":  0.817383
                  },
                  {
                      "player":  "Alec Burleson",
                      "team":  "STL",
                      "opp":  "CHC",
                      "stat":  "HITTER FANTASY SCORE",
                      "line":  2.5,
                      "dir":  "OVER",
                      "tier":  "GOBLIN",
                      "p_cal":  0.814453
                  },
                  {
                      "player":  "Munetaka Murakami",
                      "team":  "CWS",
                      "opp":  "DET",
                      "stat":  "HITTER FANTASY SCORE",
                      "line":  1.5,
                      "dir":  "OVER",
                      "tier":  "GOBLIN",
                      "p_cal":  0.808105
                  },
                  {
                      "player":  "Owen Caissie",
                      "team":  "MIA",
                      "opp":  "NYM",
                      "stat":  "HITTER STRIKEOUTS",
                      "line":  0.5,
                      "dir":  "OVER",
                      "tier":  "GOBLIN",
                      "p_cal":  0.791992
                  },
                  {
                      "player":  "JJ Bleday",
                      "team":  "CIN",
                      "opp":  "ATL",
                      "stat":  "HITTER FANTASY SCORE",
                      "line":  2.5,
                      "dir":  "OVER",
                      "tier":  "GOBLIN",
                      "p_cal":  0.790527
                  },
                  {
                      "player":  "Michael Lorenzen",
                      "team":  "COL",
                      "opp":  "SF",
                      "stat":  "WALKS ALLOWED",
                      "line":  0.5,
                      "dir":  "OVER",
                      "tier":  "GOBLIN",
                      "p_cal":  0.790039
                  },
                  {
                      "player":  "Shohei Ohtani",
                      "team":  "LAD",
                      "opp":  "PHI",
                      "stat":  "HITTER STRIKEOUTS",
                      "line":  0.5,
                      "dir":  "OVER",
                      "tier":  "GOBLIN",
                      "p_cal":  0.785645
                  },
                  {
                      "player":  "CJ Abrams",
                      "team":  "WSH",
                      "opp":  "SD",
                      "stat":  "HITTER FANTASY SCORE",
                      "line":  1.5,
                      "dir":  "OVER",
                      "tier":  "GOBLIN",
                      "p_cal":  0.78418
                  },
                  {
                      "player":  "George Kirby",
                      "team":  "SEA",
                      "opp":  "AZ",
                      "stat":  "WALKS ALLOWED",
                      "line":  0.5,
                      "dir":  "OVER",
                      "tier":  "GOBLIN",
                      "p_cal":  0.783203
                  },
                  {
                      "player":  "Kai-Wei Teng",
                      "team":  "HOU",
                      "opp":  "MIL",
                      "stat":  "PITCHER FANTASY SCORE",
                      "line":  17.5,
                      "dir":  "OVER",
                      "tier":  "GOBLIN",
                      "p_cal":  0.782227
                  },
                  {
                      "player":  "Sal Stewart",
                      "team":  "CIN",
                      "opp":  "ATL",
                      "stat":  "HITTER FANTASY SCORE",
                      "line":  1.5,
                      "dir":  "OVER",
                      "tier":  "GOBLIN",
                      "p_cal":  0.780273
                  },
                  {
                      "player":  "Carson Benge",
                      "team":  "NYM",
                      "opp":  "MIA",
                      "stat":  "HITTER FANTASY SCORE",
                      "line":  2.5,
                      "dir":  "OVER",
                      "tier":  "GOBLIN",
                      "p_cal":  0.779785
                  },
                  {
                      "player":  "Shota Imanaga",
                      "team":  "CHC",
                      "opp":  "STL",
                      "stat":  "PITCHER STRIKEOUTS",
                      "line":  3.5,
                      "dir":  "OVER",
                      "tier":  "GOBLIN",
                      "p_cal":  0.776855
                  },
                  {
                      "player":  "Pete Alonso",
                      "team":  "BAL",
                      "opp":  "TOR",
                      "stat":  "HITTER FANTASY SCORE",
                      "line":  2.5,
                      "dir":  "OVER",
                      "tier":  "GOBLIN",
                      "p_cal":  0.772461
                  },
                  {
                      "player":  "Wilyer Abreu",
                      "team":  "BOS",
                      "opp":  "CLE",
                      "stat":  "HITTER FANTASY SCORE",
                      "line":  2.5,
                      "dir":  "OVER",
                      "tier":  "GOBLIN",
                      "p_cal":  0.770996
                  },
                  {
                      "player":  "Jarren Duran",
                      "team":  "BOS",
                      "opp":  "CLE",
                      "stat":  "HITTER FANTASY SCORE",
                      "line":  2.5,
                      "dir":  "OVER",
                      "tier":  "GOBLIN",
                      "p_cal":  0.770508
                  },
                  {
                      "player":  "Ketel Marte",
                      "team":  "AZ",
                      "opp":  "SEA",
                      "stat":  "HITTER FANTASY SCORE",
                      "line":  2.5,
                      "dir":  "OVER",
                      "tier":  "GOBLIN",
                      "p_cal":  0.768066
                  },
                  {
                      "player":  "Shea Langeliers",
                      "team":  "ATH",
                      "opp":  "NYY",
                      "stat":  "HITTER FANTASY SCORE",
                      "line":  2.5,
                      "dir":  "OVER",
                      "tier":  "GOBLIN",
                      "p_cal":  0.767578
                  },
                  {
                      "player":  "Luis Severino",
                      "team":  "ATH",
                      "opp":  "NYY",
                      "stat":  "HITS ALLOWED",
                      "line":  3.5,
                      "dir":  "OVER",
                      "tier":  "GOBLIN",
                      "p_cal":  0.76709
                  },
                  {
                      "player":  "Ramón Laureano",
                      "team":  "SD",
                      "opp":  "WSH",
                      "stat":  "HITTER STRIKEOUTS",
                      "line":  0.5,
                      "dir":  "OVER",
                      "tier":  "GOBLIN",
                      "p_cal":  0.76709
                  },
                  {
                      "player":  "Brent Rooker",
                      "team":  "ATH",
                      "opp":  "NYY",
                      "stat":  "HITTER STRIKEOUTS",
                      "line":  0.5,
                      "dir":  "OVER",
                      "tier":  "GOBLIN",
                      "p_cal":  0.766113
                  },
                  {
                      "player":  "Bobby Witt Jr.",
                      "team":  "KC",
                      "opp":  "TEX",
                      "stat":  "HITTER FANTASY SCORE",
                      "line":  2.5,
                      "dir":  "OVER",
                      "tier":  "GOBLIN",
                      "p_cal":  0.764648
                  },
                  {
                      "player":  "Masyn Winn",
                      "team":  "STL",
                      "opp":  "CHC",
                      "stat":  "HITTER FANTASY SCORE",
                      "line":  1.5,
                      "dir":  "OVER",
                      "tier":  "GOBLIN",
                      "p_cal":  0.764648
                  },
                  {
                      "player":  "Michael Busch",
                      "team":  "CHC",
                      "opp":  "STL",
                      "stat":  "HITTER FANTASY SCORE",
                      "line":  2.5,
                      "dir":  "OVER",
                      "tier":  "GOBLIN",
                      "p_cal":  0.763184
                  },
                  {
                      "player":  "Paxton Schultz",
                      "team":  "WSH",
                      "opp":  "SD",
                      "stat":  "HITS ALLOWED",
                      "line":  0.5,
                      "dir":  "OVER",
                      "tier":  "GOBLIN",
                      "p_cal":  0.762207
                  },
                  {
                      "player":  "Colson Montgomery",
                      "team":  "CWS",
                      "opp":  "DET",
                      "stat":  "HITTER STRIKEOUTS",
                      "line":  0.5,
                      "dir":  "OVER",
                      "tier":  "GOBLIN",
                      "p_cal":  0.760742
                  },
                  {
                      "player":  "Paul Goldschmidt",
                      "team":  "NYY",
                      "opp":  "ATH",
                      "stat":  "HITTER FANTASY SCORE",
                      "line":  2.5,
                      "dir":  "OVER",
                      "tier":  "GOBLIN",
                      "p_cal":  0.759277
                  },
                  {
                      "player":  "Austin Riley",
                      "team":  "ATL",
                      "opp":  "CIN",
                      "stat":  "HITTER STRIKEOUTS",
                      "line":  0.5,
                      "dir":  "OVER",
                      "tier":  "GOBLIN",
                      "p_cal":  0.757324
                  },
                  {
                      "player":  "Marcus Semien",
                      "team":  "NYM",
                      "opp":  "MIA",
                      "stat":  "HITTER FANTASY SCORE",
                      "line":  1.5,
                      "dir":  "OVER",
                      "tier":  "GOBLIN",
                      "p_cal":  0.756348
                  },
                  {
                      "player":  "Zack Wheeler",
                      "team":  "PHI",
                      "opp":  "LAD",
                      "stat":  "PITCHER FANTASY SCORE",
                      "line":  22.5,
                      "dir":  "OVER",
                      "tier":  "GOBLIN",
                      "p_cal":  0.756348
                  },
                  {
                      "player":  "Rafael Devers",
                      "team":  "SF",
                      "opp":  "COL",
                      "stat":  "HITTER STRIKEOUTS",
                      "line":  0.5,
                      "dir":  "OVER",
                      "tier":  "GOBLIN",
                      "p_cal":  0.755371
                  },
                  {
                      "player":  "Braden Shewmake",
                      "team":  "HOU",
                      "opp":  "MIL",
                      "stat":  "HITTER FANTASY SCORE",
                      "line":  1.5,
                      "dir":  "OVER",
                      "tier":  "GOBLIN",
                      "p_cal":  0.754883
                  },
                  {
                      "player":  "Riley Greene",
                      "team":  "DET",
                      "opp":  "CWS",
                      "stat":  "HITTER FANTASY SCORE",
                      "line":  2.5,
                      "dir":  "OVER",
                      "tier":  "GOBLIN",
                      "p_cal":  0.753906
                  },
                  {
                      "player":  "Brayan Rocchio",
                      "team":  "CLE",
                      "opp":  "BOS",
                      "stat":  "HITTER FANTASY SCORE",
                      "line":  1.5,
                      "dir":  "OVER",
                      "tier":  "GOBLIN",
                      "p_cal":  0.753418
                  },
                  {
                      "player":  "Juan Soto",
                      "team":  "NYM",
                      "opp":  "MIA",
                      "stat":  "HITTER FANTASY SCORE",
                      "line":  2.5,
                      "dir":  "OVER",
                      "tier":  "GOBLIN",
                      "p_cal":  0.753418
                  },
                  {
                      "player":  "Ian Happ",
                      "team":  "CHC",
                      "opp":  "STL",
                      "stat":  "HITTER STRIKEOUTS",
                      "line":  0.5,
                      "dir":  "OVER",
                      "tier":  "GOBLIN",
                      "p_cal":  0.750977
                  },
                  {
                      "player":  "Dillon Dingler",
                      "team":  "DET",
                      "opp":  "CWS",
                      "stat":  "HITTER FANTASY SCORE",
                      "line":  2.5,
                      "dir":  "OVER",
                      "tier":  "GOBLIN",
                      "p_cal":  0.749512
                  },
                  {
                      "player":  "Konnor Griffin",
                      "team":  "PIT",
                      "opp":  "MIN",
                      "stat":  "HITTER FANTASY SCORE",
                      "line":  1.5,
                      "dir":  "OVER",
                      "tier":  "GOBLIN",
                      "p_cal":  0.749023
                  },
                  {
                      "player":  "Sam Antonacci",
                      "team":  "CWS",
                      "opp":  "DET",
                      "stat":  "HITTER FANTASY SCORE",
                      "line":  1.5,
                      "dir":  "OVER",
                      "tier":  "GOBLIN",
                      "p_cal":  0.749023
                  },
                  {
                      "player":  "Bryce Harper",
                      "team":  "PHI",
                      "opp":  "LAD",
                      "stat":  "HITTER FANTASY SCORE",
                      "line":  2.5,
                      "dir":  "OVER",
                      "tier":  "GOBLIN",
                      "p_cal":  0.748535
                  },
                  {
                      "player":  "Gabriel Moreno",
                      "team":  "AZ",
                      "opp":  "SEA",
                      "stat":  "HITTER FANTASY SCORE",
                      "line":  1.5,
                      "dir":  "OVER",
                      "tier":  "GOBLIN",
                      "p_cal":  0.74707
                  },
                  {
                      "player":  "A.J. Ewing",
                      "team":  "NYM",
                      "opp":  "MIA",
                      "stat":  "HITTER FANTASY SCORE",
                      "line":  1.5,
                      "dir":  "OVER",
                      "tier":  "GOBLIN",
                      "p_cal":  0.746582
                  },
                  {
                      "player":  "Brandon Lowe",
                      "team":  "PIT",
                      "opp":  "MIN",
                      "stat":  "HITTER FANTASY SCORE",
                      "line":  2.5,
                      "dir":  "OVER",
                      "tier":  "GOBLIN",
                      "p_cal":  0.746582
                  }
              ],
    "total_legs":  7393,
    "total_slips":  0
}