[
    {
        "n_legs":  "5",
        "legs":  "Kevin Porter UNDER PRA 28.5 (STANDARD) [id:9744383] | Ronald Holland UNDER PR 12.5 (STANDARD) [id:9747470] | Nikola Vučević OVER REB 4.5 (GOBLIN) [id:9747543] | John Collins OVER FG3M 0.5 (GOBLIN) [id:9745422] | Derrick Jones UNDER REB 2.5 (STANDARD) [id:9745411]",
        "hit_prob":  "0.3764038661968912",
        "ev_mult":  "7.528077323937824",
        "avg_p":  "0.8231270824722376",
        "avg_fragility":  "0.0",
        "leg_1":  "Kevin Porter UNDER PRA 28.5 (STANDARD) [id:9744383]",
        "leg_2":  "Ronald Holland UNDER PR 12.5 (STANDARD) [id:9747470]",
        "leg_3":  "Nikola Vučević OVER REB 4.5 (GOBLIN) [id:9747543]",
        "leg_4":  "John Collins OVER FG3M 0.5 (GOBLIN) [id:9745422]",
        "leg_5":  "Derrick Jones UNDER REB 2.5 (STANDARD) [id:9745411]",
        "slip_agreement_score":  "2",
        "slip_agreement_tier":  "AGREEMENT",
        "slip_tag":  "mixed",
        "slip_tag_set":  "late|main",
        "slip_min_start_utc":  "2026-02-07T00:40:00+00:00",
        "slip_has_unknown_start":  "0"
    },
    {
        "n_legs":  "5",
        "legs":  "Derrick White OVER REB 2.5 (GOBLIN) [id:9743822] | Ronald Holland UNDER PTS 8.5 (STANDARD) [id:9747468] | Kevin Porter UNDER REB 5 (STANDARD) [id:9744385] | Derrick Jones UNDER RA 3.5 (STANDARD) [id:9749332] | Davion Mitchell OVER AST 4.5 (GOBLIN) [id:9745884]",
        "hit_prob":  "0.3617988452066961",
        "ev_mult":  "7.2359769041339215",
        "avg_p":  "0.8176873261404454",
        "avg_fragility":  "0.0",
        "leg_1":  "Derrick White OVER REB 2.5 (GOBLIN) [id:9743822]",
        "leg_2":  "Ronald Holland UNDER PTS 8.5 (STANDARD) [id:9747468]",
        "leg_3":  "Kevin Porter UNDER REB 5 (STANDARD) [id:9744385]",
        "leg_4":  "Derrick Jones UNDER RA 3.5 (STANDARD) [id:9749332]",
        "leg_5":  "Davion Mitchell OVER AST 4.5 (GOBLIN) [id:9745884]",
        "slip_agreement_score":  "2",
        "slip_agreement_tier":  "AGREEMENT",
        "slip_tag":  "mixed",
        "slip_tag_set":  "late|main",
        "slip_min_start_utc":  "2026-02-07T00:40:00+00:00",
        "slip_has_unknown_start":  "0"
    },
    {
        "n_legs":  "5",
        "legs":  "Andrew Wiggins OVER REB 3.5 (GOBLIN) [id:9741988] | Trey Murphy UNDER PR 27.5 (STANDARD) [id:9742897] | Kevin Porter UNDER PTS 16.5 (STANDARD) [id:9744380] | Derrick White OVER REB 2.5 (GOBLIN) [id:9743822] | Derrick Jones UNDER REB 2.5 (STANDARD) [id:9745411]",
        "hit_prob":  "0.3563534034038401",
        "ev_mult":  "7.127068068076802",
        "avg_p":  "0.8154892430921603",
        "avg_fragility":  "0.0",
        "leg_1":  "Andrew Wiggins OVER REB 3.5 (GOBLIN) [id:9741988]",
        "leg_2":  "Trey Murphy UNDER PR 27.5 (STANDARD) [id:9742897]",
        "leg_3":  "Kevin Porter UNDER PTS 16.5 (STANDARD) [id:9744380]",
        "leg_4":  "Derrick White OVER REB 2.5 (GOBLIN) [id:9743822]",
        "leg_5":  "Derrick Jones UNDER REB 2.5 (STANDARD) [id:9745411]",
        "slip_agreement_score":  "2",
        "slip_agreement_tier":  "AGREEMENT",
        "slip_tag":  "mixed",
        "slip_tag_set":  "late|main",
        "slip_min_start_utc":  "2026-02-07T00:40:00+00:00",
        "slip_has_unknown_start":  "0"
    },
    {
        "n_legs":  "5",
        "legs":  "Trey Murphy UNDER REB 5 (STANDARD) [id:9748360] | Jeremiah Fears OVER REB 1.5 (GOBLIN) [id:9744975] | Kevin Porter UNDER REB 5 (STANDARD) [id:9744385] | Donte DiVincenzo OVER REB 3.5 (GOBLIN) [id:9743175] | Nikola Vučević OVER PA 11.5 (GOBLIN) [id:9747505]",
        "hit_prob":  "0.3528099776885017",
        "ev_mult":  "7.056199553770036",
        "avg_p":  "0.8140465745154376",
        "avg_fragility":  "8.661758336941446e-05",
        "leg_1":  "Trey Murphy UNDER REB 5 (STANDARD) [id:9748360]",
        "leg_2":  "Jeremiah Fears OVER REB 1.5 (GOBLIN) [id:9744975]",
        "leg_3":  "Kevin Porter UNDER REB 5 (STANDARD) [id:9744385]",
        "leg_4":  "Donte DiVincenzo OVER REB 3.5 (GOBLIN) [id:9743175]",
        "leg_5":  "Nikola Vučević OVER PA 11.5 (GOBLIN) [id:9747505]",
        "slip_agreement_score":  "2",
        "slip_agreement_tier":  "AGREEMENT",
        "slip_tag":  "main",
        "slip_tag_set":  "main",
        "slip_min_start_utc":  "2026-02-07T00:40:00+00:00",
        "slip_has_unknown_start":  "0"
    },
    {
        "n_legs":  "5",
        "legs":  "Yanic Niederhäuser UNDER PTS 7.5 (STANDARD) [id:9746628] | T.J. McConnell OVER AST 2.5 (GOBLIN) [id:9750331] | Deni Avdija OVER PA 24.5 (GOBLIN) [id:9748864] | Trey Murphy UNDER PA 26.5 (STANDARD) [id:9742717] | Derrick White OVER REB 2.5 (GOBLIN) [id:9743822]",
        "hit_prob":  "0.3496880992871735",
        "ev_mult":  "6.993761985743471",
        "avg_p":  "0.8132240960992508",
        "avg_fragility":  "0.0",
        "leg_1":  "Yanic Niederhäuser UNDER PTS 7.5 (STANDARD) [id:9746628]",
        "leg_2":  "T.J. McConnell OVER AST 2.5 (GOBLIN) [id:9750331]",
        "leg_3":  "Deni Avdija OVER PA 24.5 (GOBLIN) [id:9748864]",
        "leg_4":  "Trey Murphy UNDER PA 26.5 (STANDARD) [id:9742717]",
        "leg_5":  "Derrick White OVER REB 2.5 (GOBLIN) [id:9743822]",
        "slip_agreement_score":  "2",
        "slip_agreement_tier":  "AGREEMENT",
        "slip_tag":  "mixed",
        "slip_tag_set":  "late|main",
        "slip_min_start_utc":  "2026-02-07T00:40:00+00:00",
        "slip_has_unknown_start":  "0"
    },
    {
        "n_legs":  "5",
        "legs":  "Neemias Queta OVER PTS 4.5 (GOBLIN) [id:9748498] | DeMar DeRozan OVER RA 4.5 (GOBLIN) [id:9747529] | T.J. McConnell OVER AST 2.5 (GOBLIN) [id:9750331] | Kevin Porter UNDER PA 22.5 (STANDARD) [id:9744381] | Jaylen Wells OVER AST 0.5 (GOBLIN) [id:9745295]",
        "hit_prob":  "0.340961559701266",
        "ev_mult":  "6.819231194025321",
        "avg_p":  "0.8082536081588861",
        "avg_fragility":  "9.295840111551636e-05",
        "leg_1":  "Neemias Queta OVER PTS 4.5 (GOBLIN) [id:9748498]",
        "leg_2":  "DeMar DeRozan OVER RA 4.5 (GOBLIN) [id:9747529]",
        "leg_3":  "T.J. McConnell OVER AST 2.5 (GOBLIN) [id:9750331]",
        "leg_4":  "Kevin Porter UNDER PA 22.5 (STANDARD) [id:9744381]",
        "leg_5":  "Jaylen Wells OVER AST 0.5 (GOBLIN) [id:9745295]",
        "slip_agreement_score":  "2",
        "slip_agreement_tier":  "AGREEMENT",
        "slip_tag":  "mixed",
        "slip_tag_set":  "late|main",
        "slip_min_start_utc":  "2026-02-07T00:40:00+00:00",
        "slip_has_unknown_start":  "0"
    },
    {
        "n_legs":  "5",
        "legs":  "Nikola Vučević OVER AST 1.5 (GOBLIN) [id:9747157] | Jrue Holiday OVER PA 14.5 (GOBLIN) [id:9748882] | Jalen Brunson OVER PTS 19.5 (GOBLIN) [id:9747166] | Neemias Queta OVER PTS 4.5 (GOBLIN) [id:9748498] | Yanic Niederhäuser UNDER PTS 7.5 (STANDARD) [id:9746628]",
        "hit_prob":  "0.3357029269115511",
        "ev_mult":  "6.714058538231022",
        "avg_p":  "0.8080383120846969",
        "avg_fragility":  "0.0020743684254934",
        "leg_1":  "Nikola Vučević OVER AST 1.5 (GOBLIN) [id:9747157]",
        "leg_2":  "Jrue Holiday OVER PA 14.5 (GOBLIN) [id:9748882]",
        "leg_3":  "Jalen Brunson OVER PTS 19.5 (GOBLIN) [id:9747166]",
        "leg_4":  "Neemias Queta OVER PTS 4.5 (GOBLIN) [id:9748498]",
        "leg_5":  "Yanic Niederhäuser UNDER PTS 7.5 (STANDARD) [id:9746628]",
        "slip_agreement_score":  "2",
        "slip_agreement_tier":  "AGREEMENT",
        "slip_tag":  "mixed",
        "slip_tag_set":  "late|main",
        "slip_min_start_utc":  "2026-02-07T00:40:00+00:00",
        "slip_has_unknown_start":  "0"
    },
    {
        "n_legs":  "5",
        "legs":  "Ronald Holland UNDER PR 12.5 (STANDARD) [id:9747470] | Gary Trent UNDER PTS 8.5 (STANDARD) [id:9745932] | Derik Queen OVER RA 8.5 (GOBLIN) [id:9744867] | Jaime Jaquez UNDER PRA 23.5 (STANDARD) [id:9741816] | Kevin Porter UNDER PTS 16.5 (STANDARD) [id:9744380]",
        "hit_prob":  "0.3344981506723333",
        "ev_mult":  "6.6899630134466666",
        "avg_p":  "0.8039877737161121",
        "avg_fragility":  "0.0004716981132075",
        "leg_1":  "Ronald Holland UNDER PR 12.5 (STANDARD) [id:9747470]",
        "leg_2":  "Gary Trent UNDER PTS 8.5 (STANDARD) [id:9745932]",
        "leg_3":  "Derik Queen OVER RA 8.5 (GOBLIN) [id:9744867]",
        "leg_4":  "Jaime Jaquez UNDER PRA 23.5 (STANDARD) [id:9741816]",
        "leg_5":  "Kevin Porter UNDER PTS 16.5 (STANDARD) [id:9744380]",
        "slip_agreement_score":  "2",
        "slip_agreement_tier":  "AGREEMENT",
        "slip_tag":  "main",
        "slip_tag_set":  "main",
        "slip_min_start_utc":  "2026-02-07T00:40:00+00:00",
        "slip_has_unknown_start":  "0"
    },
    {
        "n_legs":  "5",
        "legs":  "Jeremiah Fears OVER REB 1.5 (GOBLIN) [id:9744975] | Derrick Jones UNDER PTS 8.5 (STANDARD) [id:9745408] | Jaime Jaquez UNDER AST 4 (STANDARD) [id:9742020] | Cedric Coward OVER FG3M 0.5 (GOBLIN) [id:9747488] | Derik Queen OVER REB 5.5 (GOBLIN) [id:9743167]",
        "hit_prob":  "0.3340924364010096",
        "ev_mult":  "6.681848728020193",
        "avg_p":  "0.8047219295416431",
        "avg_fragility":  "8.661758336941446e-05",
        "leg_1":  "Jeremiah Fears OVER REB 1.5 (GOBLIN) [id:9744975]",
        "leg_2":  "Derrick Jones UNDER PTS 8.5 (STANDARD) [id:9745408]",
        "leg_3":  "Jaime Jaquez UNDER AST 4 (STANDARD) [id:9742020]",
        "leg_4":  "Cedric Coward OVER FG3M 0.5 (GOBLIN) [id:9747488]",
        "leg_5":  "Derik Queen OVER REB 5.5 (GOBLIN) [id:9743167]",
        "slip_agreement_score":  "1",
        "slip_agreement_tier":  "ATLAS",
        "slip_tag":  "mixed",
        "slip_tag_set":  "late|main",
        "slip_min_start_utc":  "2026-02-07T00:40:00+00:00",
        "slip_has_unknown_start":  "0"
    },
    {
        "n_legs":  "5",
        "legs":  "Jaime Jaquez UNDER AST 4 (STANDARD) [id:9742020] | Derrick Jones UNDER PTS 8.5 (STANDARD) [id:9745408] | Trey Murphy UNDER REB 5 (STANDARD) [id:9748360] | Nikola Vučević OVER AST 2.5 (STANDARD) [id:9742045] | Norman Powell OVER AST 1.5 (GOBLIN) [id:9742060]",
        "hit_prob":  "0.3333066705572507",
        "ev_mult":  "6.666133411145014",
        "avg_p":  "0.8042003505132366",
        "avg_fragility":  "0.0",
        "leg_1":  "Jaime Jaquez UNDER AST 4 (STANDARD) [id:9742020]",
        "leg_2":  "Derrick Jones UNDER PTS 8.5 (STANDARD) [id:9745408]",
        "leg_3":  "Trey Murphy UNDER REB 5 (STANDARD) [id:9748360]",
        "leg_4":  "Nikola Vučević OVER AST 2.5 (STANDARD) [id:9742045]",
        "leg_5":  "Norman Powell OVER AST 1.5 (GOBLIN) [id:9742060]",
        "slip_agreement_score":  "1",
        "slip_agreement_tier":  "ATLAS",
        "slip_tag":  "mixed",
        "slip_tag_set":  "late|main",
        "slip_min_start_utc":  "2026-02-07T00:40:00+00:00",
        "slip_has_unknown_start":  "0"
    },
    {
        "n_legs":  "5",
        "legs":  "Gary Trent UNDER PTS 8.5 (STANDARD) [id:9745932] | Kevin Porter UNDER AST 6.5 (STANDARD) [id:9746522] | Ronald Holland UNDER REB 4 (STANDARD) [id:9747471] | Andrew Wiggins OVER REB 3.5 (GOBLIN) [id:9741988] | Josh Hart OVER AST 3.5 (GOBLIN) [id:9747172]",
        "hit_prob":  "0.3291455448927376",
        "ev_mult":  "6.582910897854752",
        "avg_p":  "0.8021885456893824",
        "avg_fragility":  "0.0",
        "leg_1":  "Gary Trent UNDER PTS 8.5 (STANDARD) [id:9745932]",
        "leg_2":  "Kevin Porter UNDER AST 6.5 (STANDARD) [id:9746522]",
        "leg_3":  "Ronald Holland UNDER REB 4 (STANDARD) [id:9747471]",
        "leg_4":  "Andrew Wiggins OVER REB 3.5 (GOBLIN) [id:9741988]",
        "leg_5":  "Josh Hart OVER AST 3.5 (GOBLIN) [id:9747172]",
        "slip_agreement_score":  "1",
        "slip_agreement_tier":  "ATLAS",
        "slip_tag":  "main",
        "slip_tag_set":  "main",
        "slip_min_start_utc":  "2026-02-07T00:40:00+00:00",
        "slip_has_unknown_start":  "0"
    },
    {
        "n_legs":  "5",
        "legs":  "Jaylen Wells OVER AST 0.5 (GOBLIN) [id:9745295] | Russell Westbrook OVER PTS 13.5 (STANDARD) [id:9743061] | Nikola Vučević OVER PTS 10.5 (GOBLIN) [id:9743924] | Derrick White OVER REB 2.5 (GOBLIN) [id:9743822] | Trey Murphy UNDER AST 4 (STANDARD) [id:9742715]",
        "hit_prob":  "0.3281632540409177",
        "ev_mult":  "6.563265080818353",
        "avg_p":  "0.8025238464933582",
        "avg_fragility":  "0.0002053915275994",
        "leg_1":  "Jaylen Wells OVER AST 0.5 (GOBLIN) [id:9745295]",
        "leg_2":  "Russell Westbrook OVER PTS 13.5 (STANDARD) [id:9743061]",
        "leg_3":  "Nikola Vučević OVER PTS 10.5 (GOBLIN) [id:9743924]",
        "leg_4":  "Derrick White OVER REB 2.5 (GOBLIN) [id:9743822]",
        "leg_5":  "Trey Murphy UNDER AST 4 (STANDARD) [id:9742715]",
        "slip_agreement_score":  "1",
        "slip_agreement_tier":  "ATLAS",
        "slip_tag":  "mixed",
        "slip_tag_set":  "late|main",
        "slip_min_start_utc":  "2026-02-07T00:40:00+00:00",
        "slip_has_unknown_start":  "0"
    },
    {
        "n_legs":  "5",
        "legs":  "Jeremiah Fears OVER REB 1.5 (GOBLIN) [id:9744975] | Bobby Portis OVER FG3M 0.5 (GOBLIN) [id:9746461] | Yanic Niederhäuser UNDER REB 5.5 (STANDARD) [id:9745483] | Mitchell Robinson OVER REB 6.5 (GOBLIN) [id:9748527] | Pascal Siakam OVER PR 24.5 (GOBLIN) [id:9750668]",
        "hit_prob":  "0.3217348970383153",
        "ev_mult":  "6.4346979407663065",
        "avg_p":  "0.7988102158934381",
        "avg_fragility":  "0.0002760563709611",
        "leg_1":  "Jeremiah Fears OVER REB 1.5 (GOBLIN) [id:9744975]",
        "leg_2":  "Bobby Portis OVER FG3M 0.5 (GOBLIN) [id:9746461]",
        "leg_3":  "Yanic Niederhäuser UNDER REB 5.5 (STANDARD) [id:9745483]",
        "leg_4":  "Mitchell Robinson OVER REB 6.5 (GOBLIN) [id:9748527]",
        "leg_5":  "Pascal Siakam OVER PR 24.5 (GOBLIN) [id:9750668]",
        "slip_agreement_score":  "2",
        "slip_agreement_tier":  "AGREEMENT",
        "slip_tag":  "mixed",
        "slip_tag_set":  "late|main",
        "slip_min_start_utc":  "2026-02-07T00:40:00+00:00",
        "slip_has_unknown_start":  "0"
    },
    {
        "n_legs":  "5",
        "legs":  "Nikola Vučević OVER FG3M 0.5 (GOBLIN) [id:9742042] | Yves Missi OVER AST 0.5 (GOBLIN) [id:9745128] | Jeremiah Fears OVER REB 1.5 (GOBLIN) [id:9744975] | Derrick Jones UNDER REB 2.5 (STANDARD) [id:9745411] | Jerami Grant OVER PR 14.5 (GOBLIN) [id:9748879]",
        "hit_prob":  "0.3197225979783923",
        "ev_mult":  "6.394451959567846",
        "avg_p":  "0.7983786121188097",
        "avg_fragility":  "8.661758336941446e-05",
        "leg_1":  "Nikola Vučević OVER FG3M 0.5 (GOBLIN) [id:9742042]",
        "leg_2":  "Yves Missi OVER AST 0.5 (GOBLIN) [id:9745128]",
        "leg_3":  "Jeremiah Fears OVER REB 1.5 (GOBLIN) [id:9744975]",
        "leg_4":  "Derrick Jones UNDER REB 2.5 (STANDARD) [id:9745411]",
        "leg_5":  "Jerami Grant OVER PR 14.5 (GOBLIN) [id:9748879]",
        "slip_agreement_score":  "2",
        "slip_agreement_tier":  "AGREEMENT",
        "slip_tag":  "mixed",
        "slip_tag_set":  "late|main",
        "slip_min_start_utc":  "2026-02-07T00:40:00+00:00",
        "slip_has_unknown_start":  "0"
    },
    {
        "n_legs":  "5",
        "legs":  "Jeremiah Fears OVER RA 3.5 (GOBLIN) [id:9744979] | Ronald Holland UNDER PTS 8.5 (STANDARD) [id:9747468] | Jaylen Brown OVER REB 5.5 (GOBLIN) [id:9742034] | Nikola Vučević OVER RA 9.5 (STANDARD) [id:9743961] | Yanic Niederhäuser UNDER PR 13.5 (STANDARD) [id:9745481]",
        "hit_prob":  "0.3162347961183464",
        "ev_mult":  "6.324695922366928",
        "avg_p":  "0.7948089127568718",
        "avg_fragility":  "0.0006626905235255",
        "leg_1":  "Jeremiah Fears OVER RA 3.5 (GOBLIN) [id:9744979]",
        "leg_2":  "Ronald Holland UNDER PTS 8.5 (STANDARD) [id:9747468]",
        "leg_3":  "Jaylen Brown OVER REB 5.5 (GOBLIN) [id:9742034]",
        "leg_4":  "Nikola Vučević OVER RA 9.5 (STANDARD) [id:9743961]",
        "leg_5":  "Yanic Niederhäuser UNDER PR 13.5 (STANDARD) [id:9745481]",
        "slip_agreement_score":  "2",
        "slip_agreement_tier":  "AGREEMENT",
        "slip_tag":  "mixed",
        "slip_tag_set":  "late|main",
        "slip_min_start_utc":  "2026-02-07T00:40:00+00:00",
        "slip_has_unknown_start":  "0"
    },
    {
        "n_legs":  "5",
        "legs":  "Derrick Jones UNDER PTS 8.5 (STANDARD) [id:9745408] | Nikola Vučević OVER PA 14.5 (STANDARD) [id:9742050] | Jaime Jaquez UNDER REB 5 (STANDARD) [id:9748358] | Jalen Brunson OVER PTS 19.5 (GOBLIN) [id:9747166] | Kevin Porter UNDER PRA 28.5 (STANDARD) [id:9744383]",
        "hit_prob":  "0.3160933783492708",
        "ev_mult":  "6.321867566985418",
        "avg_p":  "0.7952612001873549",
        "avg_fragility":  "0.001203912716328",
        "leg_1":  "Derrick Jones UNDER PTS 8.5 (STANDARD) [id:9745408]",
        "leg_2":  "Nikola Vučević OVER PA 14.5 (STANDARD) [id:9742050]",
        "leg_3":  "Jaime Jaquez UNDER REB 5 (STANDARD) [id:9748358]",
        "leg_4":  "Jalen Brunson OVER PTS 19.5 (GOBLIN) [id:9747166]",
        "leg_5":  "Kevin Porter UNDER PRA 28.5 (STANDARD) [id:9744383]",
        "slip_agreement_score":  "2",
        "slip_agreement_tier":  "AGREEMENT",
        "slip_tag":  "mixed",
        "slip_tag_set":  "late|main",
        "slip_min_start_utc":  "2026-02-07T00:40:00+00:00",
        "slip_has_unknown_start":  "0"
    },
    {
        "n_legs":  "5",
        "legs":  "Andrew Wiggins OVER AST 1.5 (GOBLIN) [id:9743720] | Gary Trent UNDER PTS 8.5 (STANDARD) [id:9745932] | Jerami Grant OVER PTS 12.5 (GOBLIN) [id:9746663] | Jaime Jaquez UNDER REB 5 (STANDARD) [id:9748358] | Nikola Vučević OVER PR 17.5 (GOBLIN) [id:9749428]",
        "hit_prob":  "0.3131602156175768",
        "ev_mult":  "6.263204312351536",
        "avg_p":  "0.7942104432286113",
        "avg_fragility":  "0.0",
        "leg_1":  "Andrew Wiggins OVER AST 1.5 (GOBLIN) [id:9743720]",
        "leg_2":  "Gary Trent UNDER PTS 8.5 (STANDARD) [id:9745932]",
        "leg_3":  "Jerami Grant OVER PTS 12.5 (GOBLIN) [id:9746663]",
        "leg_4":  "Jaime Jaquez UNDER REB 5 (STANDARD) [id:9748358]",
        "leg_5":  "Nikola Vučević OVER PR 17.5 (GOBLIN) [id:9749428]",
        "slip_agreement_score":  "2",
        "slip_agreement_tier":  "AGREEMENT",
        "slip_tag":  "mixed",
        "slip_tag_set":  "late|main",
        "slip_min_start_utc":  "2026-02-07T00:40:00+00:00",
        "slip_has_unknown_start":  "0"
    },
    {
        "n_legs":  "5",
        "legs":  "Jaime Jaquez UNDER PTS 13.5 (STANDARD) [id:9741813] | Ronald Holland UNDER PR 12.5 (STANDARD) [id:9747470] | Nikola Vučević OVER RA 9.5 (STANDARD) [id:9743961] | Derrick White OVER REB 2.5 (GOBLIN) [id:9743822] | T.J. McConnell OVER PRA 12.5 (GOBLIN) [id:9746589]",
        "hit_prob":  "0.3126873937044726",
        "ev_mult":  "6.253747874089452",
        "avg_p":  "0.7950908529150826",
        "avg_fragility":  "0.0",
        "leg_1":  "Jaime Jaquez UNDER PTS 13.5 (STANDARD) [id:9741813]",
        "leg_2":  "Ronald Holland UNDER PR 12.5 (STANDARD) [id:9747470]",
        "leg_3":  "Nikola Vučević OVER RA 9.5 (STANDARD) [id:9743961]",
        "leg_4":  "Derrick White OVER REB 2.5 (GOBLIN) [id:9743822]",
        "leg_5":  "T.J. McConnell OVER PRA 12.5 (GOBLIN) [id:9746589]",
        "slip_agreement_score":  "2",
        "slip_agreement_tier":  "AGREEMENT",
        "slip_tag":  "main",
        "slip_tag_set":  "main",
        "slip_min_start_utc":  "2026-02-07T00:40:00+00:00",
        "slip_has_unknown_start":  "0"
    },
    {
        "n_legs":  "5",
        "legs":  "Russell Westbrook OVER PTS 12.5 (GOBLIN) [id:9746336] | Saddiq Bey OVER PTS 13.5 (GOBLIN) [id:9749534] | Jaylen Brown OVER REB 5.5 (GOBLIN) [id:9742034] | Trey Murphy UNDER AST 4 (STANDARD) [id:9742715] | Nikola Vučević OVER FG3M 0.5 (GOBLIN) [id:9742042]",
        "hit_prob":  "0.3107339901685885",
        "ev_mult":  "6.214679803371771",
        "avg_p":  "0.7928746344678357",
        "avg_fragility":  "0.0010493679942761",
        "leg_1":  "Russell Westbrook OVER PTS 12.5 (GOBLIN) [id:9746336]",
        "leg_2":  "Saddiq Bey OVER PTS 13.5 (GOBLIN) [id:9749534]",
        "leg_3":  "Jaylen Brown OVER REB 5.5 (GOBLIN) [id:9742034]",
        "leg_4":  "Trey Murphy UNDER AST 4 (STANDARD) [id:9742715]",
        "leg_5":  "Nikola Vučević OVER FG3M 0.5 (GOBLIN) [id:9742042]",
        "slip_agreement_score":  "1",
        "slip_agreement_tier":  "ATLAS",
        "slip_tag":  "mixed",
        "slip_tag_set":  "late|main",
        "slip_min_start_utc":  "2026-02-07T00:40:00+00:00",
        "slip_has_unknown_start":  "0"
    },
    {
        "n_legs":  "5",
        "legs":  "Yanic Niederhäuser UNDER PA 8.5 (STANDARD) [id:9749390] | Sam Hauser OVER REB 2.5 (GOBLIN) [id:9745889] | John Collins OVER FG3M 0.5 (GOBLIN) [id:9745422] | Josh Hart OVER AST 3.5 (GOBLIN) [id:9747172] | Trey Murphy UNDER PA 26.5 (STANDARD) [id:9742717]",
        "hit_prob":  "0.3072013773115161",
        "ev_mult":  "6.144027546230322",
        "avg_p":  "0.7898205359439862",
        "avg_fragility":  "0.0",
        "leg_1":  "Yanic Niederhäuser UNDER PA 8.5 (STANDARD) [id:9749390]",
        "leg_2":  "Sam Hauser OVER REB 2.5 (GOBLIN) [id:9745889]",
        "leg_3":  "John Collins OVER FG3M 0.5 (GOBLIN) [id:9745422]",
        "leg_4":  "Josh Hart OVER AST 3.5 (GOBLIN) [id:9747172]",
        "leg_5":  "Trey Murphy UNDER PA 26.5 (STANDARD) [id:9742717]",
        "slip_agreement_score":  "2",
        "slip_agreement_tier":  "AGREEMENT",
        "slip_tag":  "mixed",
        "slip_tag_set":  "late|main",
        "slip_min_start_utc":  "2026-02-07T00:40:00+00:00",
        "slip_has_unknown_start":  "0"
    },
    {
        "n_legs":  "5",
        "legs":  "Derrick Jones UNDER PTS 8.5 (STANDARD) [id:9745408] | Jeremiah Fears OVER REB 1.5 (GOBLIN) [id:9744975] | GG Jackson UNDER PRA 21.5 (STANDARD) [id:9744572] | DeMar DeRozan OVER REB 1.5 (GOBLIN) [id:9746234] | Nikola Vučević OVER RA 8.5 (GOBLIN) [id:9743958]",
        "hit_prob":  "0.3063278733435698",
        "ev_mult":  "6.126557466871397",
        "avg_p":  "0.7913734215065367",
        "avg_fragility":  "0.0021383571016566",
        "leg_1":  "Derrick Jones UNDER PTS 8.5 (STANDARD) [id:9745408]",
        "leg_2":  "Jeremiah Fears OVER REB 1.5 (GOBLIN) [id:9744975]",
        "leg_3":  "GG Jackson UNDER PRA 21.5 (STANDARD) [id:9744572]",
        "leg_4":  "DeMar DeRozan OVER REB 1.5 (GOBLIN) [id:9746234]",
        "leg_5":  "Nikola Vučević OVER RA 8.5 (GOBLIN) [id:9743958]",
        "slip_agreement_score":  "2",
        "slip_agreement_tier":  "AGREEMENT",
        "slip_tag":  "mixed",
        "slip_tag_set":  "late|main",
        "slip_min_start_utc":  "2026-02-07T00:40:00+00:00",
        "slip_has_unknown_start":  "0"
    },
    {
        "n_legs":  "5",
        "legs":  "Russell Westbrook OVER PR 16.5 (GOBLIN) [id:9749587] | Derrick Jones UNDER REB 2.5 (STANDARD) [id:9745411] | Jarace Walker UNDER REB 5.5 (STANDARD) [id:9744334] | Ronald Holland UNDER PTS 8.5 (STANDARD) [id:9747468] | Jaime Jaquez UNDER REB 5 (STANDARD) [id:9748358]",
        "hit_prob":  "0.3048401139878081",
        "ev_mult":  "6.0968022797561625",
        "avg_p":  "0.7907483542357907",
        "avg_fragility":  "0.0027322894254522",
        "leg_1":  "Russell Westbrook OVER PR 16.5 (GOBLIN) [id:9749587]",
        "leg_2":  "Derrick Jones UNDER REB 2.5 (STANDARD) [id:9745411]",
        "leg_3":  "Jarace Walker UNDER REB 5.5 (STANDARD) [id:9744334]",
        "leg_4":  "Ronald Holland UNDER PTS 8.5 (STANDARD) [id:9747468]",
        "leg_5":  "Jaime Jaquez UNDER REB 5 (STANDARD) [id:9748358]",
        "slip_agreement_score":  "2",
        "slip_agreement_tier":  "AGREEMENT",
        "slip_tag":  "mixed",
        "slip_tag_set":  "late|main",
        "slip_min_start_utc":  "2026-02-07T00:40:00+00:00",
        "slip_has_unknown_start":  "0"
    },
    {
        "n_legs":  "5",
        "legs":  "Gary Trent UNDER PRA 12.5 (STANDARD) [id:9750089] | Derrick Jones UNDER PTS 8.5 (STANDARD) [id:9745408] | Yanic Niederhäuser UNDER PA 8.5 (STANDARD) [id:9749390] | Duncan Robinson OVER RA 2.5 (GOBLIN) [id:9748008] | Jaime Jaquez UNDER PR 18.5 (STANDARD) [id:9741815]",
        "hit_prob":  "0.3042357055723216",
        "ev_mult":  "6.084714111446433",
        "avg_p":  "0.7892363106095763",
        "avg_fragility":  "0.0",
        "leg_1":  "Gary Trent UNDER PRA 12.5 (STANDARD) [id:9750089]",
        "leg_2":  "Derrick Jones UNDER PTS 8.5 (STANDARD) [id:9745408]",
        "leg_3":  "Yanic Niederhäuser UNDER PA 8.5 (STANDARD) [id:9749390]",
        "leg_4":  "Duncan Robinson OVER RA 2.5 (GOBLIN) [id:9748008]",
        "leg_5":  "Jaime Jaquez UNDER PR 18.5 (STANDARD) [id:9741815]",
        "slip_agreement_score":  "2",
        "slip_agreement_tier":  "AGREEMENT",
        "slip_tag":  "mixed",
        "slip_tag_set":  "late|main",
        "slip_min_start_utc":  "2026-02-07T00:40:00+00:00",
        "slip_has_unknown_start":  "0"
    },
    {
        "n_legs":  "5",
        "legs":  "Jrue Holiday OVER AST 3.5 (GOBLIN) [id:9747493] | Nikola Vučević OVER FG3M 0.5 (GOBLIN) [id:9742042] | OG Anunoby OVER PTS 11.5 (GOBLIN) [id:9748366] | DeMar DeRozan OVER AST 2.5 (GOBLIN) [id:9746223] | Derrick Jones UNDER RA 3.5 (STANDARD) [id:9749332]",
        "hit_prob":  "0.3023381651120938",
        "ev_mult":  "6.046763302241876",
        "avg_p":  "0.7879945771661541",
        "avg_fragility":  "0.0",
        "leg_1":  "Jrue Holiday OVER AST 3.5 (GOBLIN) [id:9747493]",
        "leg_2":  "Nikola Vučević OVER FG3M 0.5 (GOBLIN) [id:9742042]",
        "leg_3":  "OG Anunoby OVER PTS 11.5 (GOBLIN) [id:9748366]",
        "leg_4":  "DeMar DeRozan OVER AST 2.5 (GOBLIN) [id:9746223]",
        "leg_5":  "Derrick Jones UNDER RA 3.5 (STANDARD) [id:9749332]",
        "slip_agreement_score":  "2",
        "slip_agreement_tier":  "AGREEMENT",
        "slip_tag":  "mixed",
        "slip_tag_set":  "late|main",
        "slip_min_start_utc":  "2026-02-07T00:40:00+00:00",
        "slip_has_unknown_start":  "0"
    },
    {
        "n_legs":  "5",
        "legs":  "Josh Hart OVER AST 3.5 (GOBLIN) [id:9747172] | Naz Reid OVER AST 1.5 (GOBLIN) [id:9743194] | Nikola Vučević OVER FG3M 0.5 (GOBLIN) [id:9742042] | Derrick Jones UNDER PRA 12.5 (STANDARD) [id:9749330] | Jaime Jaquez UNDER PTS 13.5 (STANDARD) [id:9741813]",
        "hit_prob":  "0.3021675236182265",
        "ev_mult":  "6.04335047236453",
        "avg_p":  "0.789149502157626",
        "avg_fragility":  "0.0",
        "leg_1":  "Josh Hart OVER AST 3.5 (GOBLIN) [id:9747172]",
        "leg_2":  "Naz Reid OVER AST 1.5 (GOBLIN) [id:9743194]",
        "leg_3":  "Nikola Vučević OVER FG3M 0.5 (GOBLIN) [id:9742042]",
        "leg_4":  "Derrick Jones UNDER PRA 12.5 (STANDARD) [id:9749330]",
        "leg_5":  "Jaime Jaquez UNDER PTS 13.5 (STANDARD) [id:9741813]",
        "slip_agreement_score":  "2",
        "slip_agreement_tier":  "AGREEMENT",
        "slip_tag":  "mixed",
        "slip_tag_set":  "late|main",
        "slip_min_start_utc":  "2026-02-07T00:40:00+00:00",
        "slip_has_unknown_start":  "0"
    }
]
